{
    "Rechnungen": [
        "Rechnungen"
    ],
    "Unterlagen": [
        "Unterlagen"
    ],
    "Jahre": [
        "Jahre"
    ],
    "Finanzamt": [
        "Finanzamt"
    ],
    "Informationen": [
        "Informationen"
    ],
    "Fragen": [
        "Fragen"
    ],
    "AirBnB": [
        "AirBnB"
    ],
    "Steuererklärungen": [
        "Steuererklärungen"
    ],
    "Zahlungen": [
        "Zahlungen"
    ],
    "Aufstellung": [
        "Aufstellung"
    ],
    "Steuererklärung": [
        "Steuererklärung"
    ],
    "Frist": [
        "Frist"
    ],
    "DATEV": [
        "DATEV"
    ],
    "Jahres": [
        "Jahres"
    ],
    "Einkommensteuererklärung": [
        "Einkommensteuererklärung"
    ],
    "Wasser": [
        "Wasser"
    ],
    "Strom": [
        "Strom"
    ],
    "Jahren": [
        "Jahren"
    ],
    "Punkte": [
        "Punkte"
    ],
    "Bearbeitung": [
        "Bearbeitung"
    ],
    "Verfügung": [
        "Verfügung"
    ],
    "Bescheid": [
        "Bescheid"
    ],
    "Sollten": [
        "Sollten"
    ],
    "Belege": [
        "Belege"
    ],
    "Rechnung": [
        "Rechnung"
    ],
    "Umsätze": [
        "Umsätze"
    ],
    "Zuordnung": [
        "Zuordnung"
    ],
    "Selbstanzeige": [
        "Selbstanzeige"
    ],
    "Beträge": [
        "Beträge"
    ],
    "Daten": [
        "Daten"
    ],
    "Promenadenstraße": [
        "Promenadenstraße"
    ],
    "Umsatzsteuer": [
        "Umsatzsteuer"
    ],
    "Fertigstellung": [
        "Fertigstellung"
    ],
    "Upload": [
        "Upload"
    ],
    "Servicegebühren": [
        "Servicegebühren"
    ],
    "Umsatzsteuererklärung": [
        "Umsatzsteuererklärung"
    ],
    "Rückfragen": [
        "Rückfragen"
    ],
    "Dedolphstraße": [
        "Dedolphstraße"
    ],
    "Wohnung": [
        "Wohnung"
    ],
    "Meine": [
        "Meine"
    ],
    "Einreichung": [
        "Einreichung"
    ],
    "Portal": [
        "Portal"
    ],
    "Abgabe": [
        "Abgabe"
    ],
    "Anlagen": [
        "Anlagen"
    ],
    "Vermietung": [
        "Vermietung"
    ],
    "Dokumente": [
        "Dokumente"
    ],
    "Begründung": [
        "Begründung"
    ],
    "Vermögensakademie": [
        "Vermögensakademie"
    ],
    "Hinsichtlich": [
        "Hinsichtlich"
    ],
    "Anlage": [
        "Anlage"
    ],
    "Steuern": [
        "Steuern"
    ],
    "Einkommensteuererklärungen": [
        "Einkommensteuererklärungen"
    ],
    "Prüfung": [
        "Prüfung"
    ],
    "Antworten": [
        "Antworten"
    ],
    "Werbungskosten": [
        "Werbungskosten"
    ],
    "Arbeit": [
        "Arbeit"
    ],
    "Finanzamtes": [
        "Finanzamtes"
    ],
    "Hintergrund": [
        "Hintergrund"
    ],
    "Antwort": [
        "Antwort"
    ],
    "Monat": [
        "Monat"
    ],
    "Aussetzung": [
        "Aussetzung"
    ],
    "Datev": [
        "Datev"
    ],
    "Sicht": [
        "Sicht"
    ],
    "Erstellung": [
        "Erstellung"
    ],
    "Zustimmungserklärungen": [
        "Zustimmungserklärungen"
    ],
    "Essen": [
        "Essen"
    ],
    "Rückmeldung": [
        "Rückmeldung"
    ],
    "Zustimmungserklärung": [
        "Zustimmungserklärung"
    ],
    "Tätigkeiten": [
        "Tätigkeiten"
    ],
    "Damit": [
        "Damit"
    ],
    "Anforderungen": [
        "Anforderungen"
    ],
    "Airbnb": [
        "Airbnb"
    ],
    "Anteil": [
        "Anteil"
    ],
    "Anzahl": [
        "Anzahl"
    ],
    "Unterhaltszahlung": [
        "Unterhaltszahlung"
    ],
    "Übersicht": [
        "Übersicht"
    ],
    "Energiekosten": [
        "Energiekosten"
    ],
    "Versorger": [
        "Versorger"
    ],
    "Sofern": [
        "Sofern"
    ],
    "Nachricht": [
        "Nachricht"
    ],
    "Zusammenhang": [
        "Zusammenhang"
    ],
    "Mitteilung": [
        "Mitteilung"
    ],
    "Unterzeichnung": [
        "Unterzeichnung"
    ],
    "Hinweis": [
        "Hinweis"
    ],
    "Nachweise": [
        "Nachweise"
    ],
    "Monate": [
        "Monate"
    ],
    "Erklärungen": [
        "Erklärungen"
    ],
    "Tätigkeit": [
        "Tätigkeit"
    ],
    "Vielleicht": [
        "Vielleicht"
    ],
    "Umsatzsteuerbescheid": [
        "Umsatzsteuerbescheid"
    ],
    "Vater": [
        "Vater"
    ],
    "Nachweis": [
        "Nachweis"
    ],
    "Verbindung": [
        "Verbindung"
    ],
    "Login": [
        "Login"
    ],
    "Schreiben": [
        "Schreiben"
    ],
    "Beantwortung": [
        "Beantwortung"
    ],
    "Erklärung": [
        "Erklärung"
    ],
    "Arbeitszimmer": [
        "Arbeitszimmer"
    ],
    "Vorbehalt": [
        "Vorbehalt"
    ],
    "Übertragung": [
        "Übertragung"
    ],
    "Einspruch": [
        "Einspruch"
    ],
    "Vollziehung": [
        "Vollziehung"
    ],
    "Vorjahres": [
        "Vorjahres"
    ],
    "Verträge": [
        "Verträge"
    ],
    "Urlaub": [
        "Urlaub"
    ],
    "Finanzseminar": [
        "Finanzseminar"
    ],
    "Frage": [
        "Frage"
    ]
}