{
    "Jahre": 38,
    "Finanzamt": 37,
    "Rechnungen": 30,
    "Fragen": 29,
    "Steuererklärungen": 25,
    "Zahlungen": 25,
    "Aufstellung": 25,
    "Steuererklärung": 23,
    "Informationen": 22,
    "Unterlagen": 21,
    "Jahres": 20,
    "Einkommensteuererklärung": 19,
    "Wasser": 19,
    "Strom": 18,
    "Jahren": 18,
    "Frist": 16,
    "Bescheid": 16,
    "Punkte": 15,
    "Sollten": 15,
    "DATEV": 15,
    "Angaben": 14,
    "Rechnung": 14,
    "Belege": 14,
    "Umsätze": 13,
    "Selbstanzeige": 13,
    "Beträge": 13,
    "Promenadenstraße": 13,
    "Umsatzsteuer": 12,
    "Bearbeitung": 11,
    "Umsatzsteuererklärung": 11,
    "Daten": 11,
    "Dedolphstraße": 11,
    "AirBnB": 11,
    "Wohnung": 11,
    "Verfügung": 11,
    "Einreichung": 10,
    "Anlagen": 10,
    "Vermietung": 10,
    "Begründung": 10,
    "Rückfragen": 10,
    "Meine": 10,
    "Anlage": 9,
    "Fertigstellung": 9,
    "Steuern": 9,
    "Archivierung": 9,
    "Posteingang": 9,
    "Einkommensteuererklärungen": 8,
    "Antworten": 8,
    "Werbungskosten": 8,
    "Dokumente": 8,
    "Arbeit": 8,
    "Upload": 8,
    "Portal": 8,
    "Monat": 7,
    "Aussetzung": 7,
    "Datev": 7,
    "Finanzamtes": 7,
    "Rückmeldung": 6,
    "Tätigkeiten": 6,
    "Prüfung": 6,
    "Anteil": 6,
    "Anzahl": 6,
    "Abgabe": 6,
    "Hinsichtlich": 6,
    "Unterhaltszahlung": 6,
    "Anhang": 6,
    "Energiekosten": 6,
    "Versorger": 6,
    "Anmerkung": 6,
    "Erstellung": 6,
    "Sofern": 6,
    "Zustimmungserklärung": 5,
    "Hintergrund": 5,
    "Erklärungen": 5,
    "Tätigkeit": 5,
    "Umsatzsteuerbescheid": 5,
    "Vater": 5,
    "Nachweis": 5,
    "Verbindung": 5,
    "Login": 5,
    "Beantwortung": 5,
    "Zustimmungserklärungen": 5,
    "Erklärung": 5,
    "Arbeitszimmer": 5,
    "Angabe": 5,
    "Übertragung": 5,
    "Sicht": 5,
    "Einspruch": 5,
    "Vollziehung": 5,
    "Vorjahres": 5,
    "Verträge": 5,
    "Essen": 5,
    "Urlaub": 4,
    "Mitteilung": 4,
    "Konsequenzen": 4,
    "Hinzu": 4,
    "Berechnungen": 4,
    "Monate": 4,
    "Betrag": 4,
    "Hierüber": 4
}